README.md
setup.py
gt_pdf_extraction/__init__.py
gt_pdf_extraction.egg-info/PKG-INFO
gt_pdf_extraction.egg-info/SOURCES.txt
gt_pdf_extraction.egg-info/dependency_links.txt
gt_pdf_extraction.egg-info/requires.txt
gt_pdf_extraction.egg-info/top_level.txt