Metadata-Version: 2.1
Name: gt-pdf-extraction
Version: 0.0.1.1
Summary: A python pdf extraction package.
Home-page: https://bitbucket.org/guangyuhe/pdf-extraction/src/main/
Author: Guangyu He
Author-email: guangyu.he@golden-tech.de
Classifier: Development Status :: 3 - Alpha
Classifier: Programming Language :: Python :: 3
Classifier: Operating System :: OS Independent
Requires-Python: >=3.10
